.project
.pydevproject
LICENSE
README
ez_setup.py
setup.cfg
setup.py
MyProxyWebService.egg-info/PKG-INFO
MyProxyWebService.egg-info/SOURCES.txt
MyProxyWebService.egg-info/dependency_links.txt
MyProxyWebService.egg-info/not-zip-safe
MyProxyWebService.egg-info/requires.txt
MyProxyWebService.egg-info/top_level.txt
documentation/Makefile
myproxy/__init__.py
myproxy/server/__init__.py
myproxy/server/wsgi/__init__.py
myproxy/server/wsgi/middleware.py
myproxy/ws/__init__.py
myproxy/ws/client/README
myproxy/ws/client/__init__.py
myproxy/ws/client/myproxy-ws-get-trustroots-wget.sh
myproxy/ws/client/myproxy-ws-get-trustroots.sh
myproxy/ws/client/myproxy-ws-logon-wget.sh
myproxy/ws/client/myproxy-ws-logon.sh
myproxy/ws/client/test/__init__.py
myproxy/ws/client/test/test_client.py
myproxy/ws/client/test/test_myproxywebservice_client.cfg
myproxy/ws/server/__init__.py
myproxy/ws/server/wsgi/__init__.py
myproxy/ws/server/wsgi/app.py
myproxy/ws/server/wsgi/httpbasicauth.py
myproxy/ws/server/wsgi/middleware.py
myproxy/ws/test/README
myproxy/ws/test/__init__.py
myproxy/ws/test/httpbasicauth.ini
myproxy/ws/test/localhost.crt
myproxy/ws/test/localhost.key
myproxy/ws/test/localhost.pem
myproxy/ws/test/myproxy_ws.py
myproxy/ws/test/myproxywsgi.ini
myproxy/ws/test/server_utils.py
myproxy/ws/test/test_httpbasicauth.py
myproxy/ws/test/test_myproxywsgi.cfg
myproxy/ws/test/test_myproxywsgi.py
myproxy/ws/test/test_myproxywsgi_with_paster.py
myproxy/ws/test/ca/530f7122.0
myproxy/ws/test/ca/7ed47087.0
myproxy/ws/test/ca/8764c6d9.0
myproxy/ws/test/ca/98ef0ee5.0
myproxy/ws/test/ca/d573507a.0
myproxy/ws/test/ca/ffc3d59b.0