Metadata-Version: 1.0
Name: MyProxyWebService
Version: 0.2.2
Summary: MyProxy Web Service
Home-page: http://proj.badc.rl.ac.uk/ndg/wiki/Security/MyProxyWebService
Author: Philip Kershaw
Author-email: Philip.Kershaw@stfc.ac.uk
License: BSD - See LICENSE file in top-level directory
Platform: POSIX
Platform: Linux
Platform: Windows
Classifier: Development Status :: 4 - Beta
Classifier: Environment :: Console
Classifier: Environment :: Web Environment
Classifier: Intended Audience :: End Users/Desktop
Classifier: Intended Audience :: Developers
Classifier: Intended Audience :: System Administrators
Classifier: Intended Audience :: Science/Research
Classifier: License :: OSI Approved :: BSD License
Classifier: Natural Language :: English
Classifier: Operating System :: Microsoft :: Windows
Classifier: Operating System :: POSIX :: Linux
Classifier: Programming Language :: Python
Classifier: Topic :: Security
Classifier: Topic :: Internet
Classifier: Topic :: Scientific/Engineering
Classifier: Topic :: System :: Distributed Computing
Classifier: Topic :: System :: Systems Administration :: Authentication/Directory
Classifier: Topic :: Software Development :: Libraries :: Python Modules
